jsonski.cpython-39-darwin.so
JSONSki-1.0.1.dist-info/LICENSE
JSONSki-1.0.1.dist-info/METADATA
JSONSki-1.0.1.dist-info/WHEEL
JSONSki-1.0.1.dist-info/top_level.txt
JSONSki-1.0.1.dist-info/RECORD
