Metadata-Version: 2.1
Name: JSONSki
Version: 1.0.1
Summary: Python binding port for JSONSki
Home-page: https://github.com/your_username/your_repository
Author: AutomataLab
Author-email: zhijia@cs.ucr.edu
License: UNKNOWN
Platform: UNKNOWN
Requires-Python: >=3.7
License-File: LICENSE
Provides-Extra: test
Requires-Dist: pytest (>=6.0) ; extra == 'test'
